vgis_code/__init__.py
vgis_code/codeGenerator.py
vgis_code-1.2.5.dist-info/METADATA
vgis_code-1.2.5.dist-info/WHEEL
vgis_code-1.2.5.dist-info/top_level.txt
vgis_code-1.2.5.dist-info/RECORD
