Metadata-Version: 2.1
Name: vgis-code
Version: 1.2.5
Summary: A libary for code generator operator
Home-page: https://github.com/gisfanmachel/vgisDatabase
Author: gisfanmachel
Author-email: gisfanmachel@gmail.com
License: UNKNOWN
Keywords: code,generator,setuptools,development
Platform: UNKNOWN
Classifier: Development Status :: 3 - Alpha
Classifier: Intended Audience :: Developers
Classifier: Topic :: Software Development :: Build Tools
Classifier: License :: OSI Approved :: MIT License
Classifier: Programming Language :: Python :: 3
Classifier: Programming Language :: Python :: 3.7
Classifier: Programming Language :: Python :: 3.8
Classifier: Programming Language :: Python :: 3.9
Classifier: Programming Language :: Python :: 3.10
Classifier: Programming Language :: Python :: 3 :: Only
Requires-Python: >=3.7, <4
Requires-Dist: vgis-utils
Requires-Dist: vgis-database
Requires-Dist: vgis-encrption
Requires-Dist: loguru
